<?xml version="1.0" encoding="utf-8" ?>
<dwsync>
<file name="base.css" server="//192.168.107.7/remote/大阪2010/OCAエコ/html/" local="129089498320000000" remote="129089498320000000" Dst="-1" />
<file name="blog.css" server="//192.168.107.7/remote/大阪2010/OCAエコ/html/" local="129089498320000000" remote="129089498320000000" Dst="-1" />
<file name="import.css" server="//192.168.107.7/remote/大阪2010/OCAエコ/html/" local="129089498310000000" remote="129089498310000000" Dst="-1" />
<file name="reset.css" server="//192.168.107.7/remote/大阪2010/OCAエコ/html/" local="129010991450000000" remote="129010991450000000" Dst="-1" />
<file name="stickyfooter.css" server="//192.168.107.7/remote/大阪2010/OCAエコ/html/" local="129053994570000000" remote="129053994570000000" Dst="-1" />
<file name="import.css" server="hptest.vista.ne.jp//osaka-eco2014/" local="129089498310000000" remote="130589515800000000" Dst="0" />
<file name="reset.css" server="hptest.vista.ne.jp//osaka-eco2014/" local="129010991450000000" remote="130589515800000000" Dst="0" />
<file name="base.css" server="hptest.vista.ne.jp//osaka-eco2014/" local="130589414706388750" remote="130589515800000000" Dst="0" />
<file name="stickyfooter.css" server="hptest.vista.ne.jp//osaka-eco2014/" local="129053994570000000" remote="130589515800000000" Dst="0" />
<file name="blog.css" server="hptest.vista.ne.jp//osaka-eco2014/" local="129089498320000000" remote="130589515800000000" Dst="0" />
</dwsync>